[ 
{"filepath": "./Sample/Assembler", "filename": "PADD.asm", "line": "INAREA   DS    0CL80                                                    ", "var_name": "INAREA", "dec_type": "DS", "data_type": "0CL80                                                    ", "group_var": 1, "valueContinuation": 0, "value": "", "datatype": "C", "varsize": 1, "isArray": 0, "multiplier": 0, "varlen": 1, "varlenInBits": 0},
{"filepath": "./Sample/Assembler", "filename": "PADD.asm", "line": "         DS    CL12                                                     ", "var_name": "", "dec_type": "DS", "data_type": "CL12                                                     ", "group_var": 0, "valueContinuation": 0, "value": "", "datatype": "C", "varsize": 12, "isArray": 0, "multiplier": 1, "varlen": 12, "varlenInBits": 0},
{"filepath": "./Sample/Assembler", "filename": "PADD.asm", "line": "INT1     DS    CL3                                                      ", "var_name": "INT1", "dec_type": "DS", "data_type": "CL3                                                      ", "group_var": 0, "valueContinuation": 0, "value": "", "datatype": "C", "varsize": 3, "isArray": 0, "multiplier": 1, "varlen": 3, "varlenInBits": 0},
{"filepath": "./Sample/Assembler", "filename": "PADD.asm", "line": "         DS    CL12                                                     ", "var_name": "", "dec_type": "DS", "data_type": "CL12                                                     ", "group_var": 0, "valueContinuation": 0, "value": "", "datatype": "C", "varsize": 12, "isArray": 0, "multiplier": 1, "varlen": 12, "varlenInBits": 0},
{"filepath": "./Sample/Assembler", "filename": "PADD.asm", "line": "INT2     DS    CL3                                                      ", "var_name": "INT2", "dec_type": "DS", "data_type": "CL3                                                      ", "group_var": 0, "valueContinuation": 0, "value": "", "datatype": "C", "varsize": 3, "isArray": 0, "multiplier": 1, "varlen": 3, "varlenInBits": 0},
{"filepath": "./Sample/Assembler", "filename": "PADD.asm", "line": "         DS    CL50                                                     ", "var_name": "", "dec_type": "DS", "data_type": "CL50                                                     ", "group_var": 0, "valueContinuation": 0, "value": "", "datatype": "C", "varsize": 50, "isArray": 0, "multiplier": 1, "varlen": 50, "varlenInBits": 0},
{"filepath": "./Sample/Assembler", "filename": "PADD.asm", "line": "OUTAREA  DS    0CL132                                                   ", "var_name": "OUTAREA", "dec_type": "DS", "data_type": "0CL132                                                   ", "group_var": 1, "valueContinuation": 0, "value": "", "datatype": "C", "varsize": 1, "isArray": 0, "multiplier": 0, "varlen": 1, "varlenInBits": 0},
{"filepath": "./Sample/Assembler", "filename": "PADD.asm", "line": "         DS    CL7' '                                                   ", "var_name": "", "dec_type": "DS", "data_type": "CL7' '                                                   ", "group_var": 0, "valueContinuation": 0, "value": " ", "datatype": "C", "varsize": 7, "isArray": 0, "multiplier": 1, "varlen": 7, "varlenInBits": 0},
{"filepath": "./Sample/Assembler", "filename": "PADD.asm", "line": "         DC    C'YOUR SUM IS '                                          ", "var_name": "", "dec_type": "DC", "data_type": "C'YOUR SUM IS '                                          ", "group_var": 0, "valueContinuation": 0, "value": "", "datatype": "C", "varsize": 1, "isArray": 0, "multiplier": 1, "varlen": 1, "varlenInBits": 0},
{"filepath": "./Sample/Assembler", "filename": "PADD.asm", "line": "SUM      DS    CL10                                                     ", "var_name": "SUM", "dec_type": "DS", "data_type": "CL10                                                     ", "group_var": 0, "valueContinuation": 0, "value": "", "datatype": "C", "varsize": 10, "isArray": 0, "multiplier": 1, "varlen": 10, "varlenInBits": 0},
{"filepath": "./Sample/Assembler", "filename": "PADD.asm", "line": "         DC    CL104' '                                                 ", "var_name": "", "dec_type": "DC", "data_type": "CL104' '                                                 ", "group_var": 0, "valueContinuation": 0, "value": " ", "datatype": "C", "varsize": 104, "isArray": 0, "multiplier": 1, "varlen": 104, "varlenInBits": 0},
{"filepath": "./Sample/Assembler", "filename": "PADD.asm", "line": "BCD      DS    D                                                        ", "var_name": "BCD", "dec_type": "DS", "data_type": "D                                                        ", "group_var": 0, "valueContinuation": 0, "value": "", "datatype": "D", "varsize": 1, "isArray": 0, "multiplier": 1, "varlen": 8, "varlenInBits": 0},
{"filepath": "./Sample/Assembler", "filename": "PADD.asm", "line": "XX1      DS    F                                                        ", "var_name": "XX1", "dec_type": "DS", "data_type": "F                                                        ", "group_var": 0, "valueContinuation": 0, "value": "", "datatype": "F", "varsize": 1, "isArray": 0, "multiplier": 1, "varlen": 4, "varlenInBits": 0},
{"filepath": "./Sample/Assembler", "filename": "PADD.asm", "line": "YY1      DS    F                                                        ", "var_name": "YY1", "dec_type": "DS", "data_type": "F                                                        ", "group_var": 0, "valueContinuation": 0, "value": "", "datatype": "F", "varsize": 1, "isArray": 0, "multiplier": 1, "varlen": 4, "varlenInBits": 0},
{"filepath": "./Sample/Assembler", "filename": "PADD.asm", "line": "ZZ1      DS    F                                                        ", "var_name": "ZZ1", "dec_type": "DS", "data_type": "F                                                        ", "group_var": 0, "valueContinuation": 0, "value": "", "datatype": "F", "varsize": 1, "isArray": 0, "multiplier": 1, "varlen": 4, "varlenInBits": 0},
{"filepath": "./Sample/Assembler", "filename": "PADD.asm", "line": "SAVE     DS    18F                                                      ", "var_name": "SAVE", "dec_type": "DS", "data_type": "18F                                                      ", "group_var": 0, "valueContinuation": 0, "value": "", "datatype": "F", "varsize": 1, "isArray": 1, "multiplier": 18, "varlen": 72, "varlenInBits": 0},
{"filepath": "./Sample/Assembler", "filename": "ASAM1.asm", "line": "         DS    0H ", "var_name": "", "dec_type": "DS", "data_type": "0H ", "group_var": 1, "valueContinuation": 0, "value": "", "datatype": "H", "varsize": 1, "isArray": 0, "multiplier": 0, "varlen": 2, "varlenInBits": 0},
{"filepath": "./Sample/Assembler", "filename": "ASAM1.asm", "line": "         DC    CL32'******** PROGRAM ASAM1 *********' ", "var_name": "", "dec_type": "DC", "data_type": "CL32'******** PROGRAM ASAM1 *********' ", "group_var": 0, "valueContinuation": 0, "value": "******** PROGRAM ASAM1 *********", "datatype": "C", "varsize": 32, "isArray": 0, "multiplier": 1, "varlen": 32, "varlenInBits": 0},
{"filepath": "./Sample/Assembler", "filename": "ASAM1.asm", "line": "EYECATCH DC    CL32'*** PROGRAM ASAM1 DATA AREAS ***' ", "var_name": "EYECATCH", "dec_type": "DC", "data_type": "CL32'*** PROGRAM ASAM1 DATA AREAS ***' ", "group_var": 0, "valueContinuation": 0, "value": "*** PROGRAM ASAM1 DATA AREAS ***", "datatype": "C", "varsize": 32, "isArray": 0, "multiplier": 1, "varlen": 32, "varlenInBits": 0},
{"filepath": "./Sample/Assembler", "filename": "ASAM1.asm", "line": "FILECC   DC    H'0'                  MAX RETURN CODE FROM FILE OPENS ", "var_name": "FILECC", "dec_type": "DC", "data_type": "H'0'                  MAX RETURN CODE FROM FILE OPENS ", "group_var": 0, "valueContinuation": 0, "value": "", "datatype": "H", "varsize": 1, "isArray": 0, "multiplier": 1, "varlen": 2, "varlenInBits": 0},
{"filepath": "./Sample/Assembler", "filename": "ASAM1.asm", "line": "RECCOUNT DC    PL4'0'                INPUT RECORD COUNT ", "var_name": "RECCOUNT", "dec_type": "DC", "data_type": "PL4'0'                INPUT RECORD COUNT ", "group_var": 0, "valueContinuation": 0, "value": "0", "datatype": "P", "varsize": 4, "isArray": 0, "multiplier": 1, "varlen": 4, "varlenInBits": 0},
{"filepath": "./Sample/Assembler", "filename": "ASAM1.asm", "line": "PROCCNT  DC    PL4'0'                PROCEDURE COUNT ", "var_name": "PROCCNT", "dec_type": "DC", "data_type": "PL4'0'                PROCEDURE COUNT ", "group_var": 0, "valueContinuation": 0, "value": "0", "datatype": "P", "varsize": 4, "isArray": 0, "multiplier": 1, "varlen": 4, "varlenInBits": 0},
{"filepath": "./Sample/Assembler", "filename": "ASAM1.asm", "line": "STATUS   DC    CL30' '               CURRENT PROGRAM STATUS ", "var_name": "STATUS", "dec_type": "DC", "data_type": "CL30' '               CURRENT PROGRAM STATUS ", "group_var": 0, "valueContinuation": 0, "value": " ", "datatype": "C", "varsize": 30, "isArray": 0, "multiplier": 1, "varlen": 30, "varlenInBits": 0},
{"filepath": "./Sample/Assembler", "filename": "ASAM1.asm", "line": "EOFFLAG  DC    XL1'00'               END OF INPUT FILE FLAG ", "var_name": "EOFFLAG", "dec_type": "DC", "data_type": "XL1'00'               END OF INPUT FILE FLAG ", "group_var": 0, "valueContinuation": 0, "value": "00", "datatype": "X", "varsize": 1, "isArray": 0, "multiplier": 1, "varlen": 1, "varlenInBits": 0},
{"filepath": "./Sample/Assembler", "filename": "ASAM1.asm", "line": "INREC    DC    CL80' '               INPUT RECORD ", "var_name": "INREC", "dec_type": "DC", "data_type": "CL80' '               INPUT RECORD ", "group_var": 0, "valueContinuation": 0, "value": " ", "datatype": "C", "varsize": 80, "isArray": 0, "multiplier": 1, "varlen": 80, "varlenInBits": 0},
{"filepath": "./Sample/Assembler", "filename": "ASAM1.asm", "line": "OUTREC   DC    CL80' '               OUTPUT RECORD ", "var_name": "OUTREC", "dec_type": "DC", "data_type": "CL80' '               OUTPUT RECORD ", "group_var": 0, "valueContinuation": 0, "value": " ", "datatype": "C", "varsize": 80, "isArray": 0, "multiplier": 1, "varlen": 80, "varlenInBits": 0},
{"filepath": "./Sample/Assembler", "filename": "ASAM1.asm", "line": "RETCODE  DC    F'0'                  DEFAULT RETURN CODE IS ZERO ", "var_name": "RETCODE", "dec_type": "DC", "data_type": "F'0'                  DEFAULT RETURN CODE IS ZERO ", "group_var": 0, "valueContinuation": 0, "value": "", "datatype": "F", "varsize": 1, "isArray": 0, "multiplier": 1, "varlen": 4, "varlenInBits": 0},
{"filepath": "./Sample/Assembler", "filename": "ASAM1.asm", "line": "MAINLSAV DC    F'0' ", "var_name": "MAINLSAV", "dec_type": "DC", "data_type": "F'0' ", "group_var": 0, "valueContinuation": 0, "value": "", "datatype": "F", "varsize": 1, "isArray": 0, "multiplier": 1, "varlen": 4, "varlenInBits": 0},
{"filepath": "./Sample/Assembler", "filename": "ASAM1.asm", "line": "OPENFSAV DC    F'0' ", "var_name": "OPENFSAV", "dec_type": "DC", "data_type": "F'0' ", "group_var": 0, "valueContinuation": 0, "value": "", "datatype": "F", "varsize": 1, "isArray": 0, "multiplier": 1, "varlen": 4, "varlenInBits": 0},
{"filepath": "./Sample/Assembler", "filename": "ASAM1.asm", "line": "CLOSFSAV DC    F'0' ", "var_name": "CLOSFSAV", "dec_type": "DC", "data_type": "F'0' ", "group_var": 0, "valueContinuation": 0, "value": "", "datatype": "F", "varsize": 1, "isArray": 0, "multiplier": 1, "varlen": 4, "varlenInBits": 0},
{"filepath": "./Sample/Assembler", "filename": "ASAM1.asm", "line": "READISAV DC    F'0' ", "var_name": "READISAV", "dec_type": "DC", "data_type": "F'0' ", "group_var": 0, "valueContinuation": 0, "value": "", "datatype": "F", "varsize": 1, "isArray": 0, "multiplier": 1, "varlen": 4, "varlenInBits": 0},
{"filepath": "./Sample/Assembler", "filename": "ASAM1.asm", "line": "WRITOSAV DC    F'0' ", "var_name": "WRITOSAV", "dec_type": "DC", "data_type": "F'0' ", "group_var": 0, "valueContinuation": 0, "value": "", "datatype": "F", "varsize": 1, "isArray": 0, "multiplier": 1, "varlen": 4, "varlenInBits": 0},
{"filepath": "./Sample/Assembler", "filename": "ASAM1.asm", "line": "OUTLINE1 DS    0CL80 ", "var_name": "OUTLINE1", "dec_type": "DS", "data_type": "0CL80 ", "group_var": 1, "valueContinuation": 0, "value": "", "datatype": "C", "varsize": 1, "isArray": 0, "multiplier": 0, "varlen": 1, "varlenInBits": 0},
{"filepath": "./Sample/Assembler", "filename": "ASAM1.asm", "line": "         DC    CL14'RECORD NUMBER ' ", "var_name": "", "dec_type": "DC", "data_type": "CL14'RECORD NUMBER ' ", "group_var": 0, "valueContinuation": 0, "value": "RECORD NUMBER ", "datatype": "C", "varsize": 14, "isArray": 0, "multiplier": 1, "varlen": 14, "varlenInBits": 0},
{"filepath": "./Sample/Assembler", "filename": "ASAM1.asm", "line": "OUTRECCT DC    CL10'          ' ", "var_name": "OUTRECCT", "dec_type": "DC", "data_type": "CL10'          ' ", "group_var": 0, "valueContinuation": 0, "value": "          ", "datatype": "C", "varsize": 10, "isArray": 0, "multiplier": 1, "varlen": 10, "varlenInBits": 0},
{"filepath": "./Sample/Assembler", "filename": "ASAM1.asm", "line": "         DC    56C' ' ", "var_name": "", "dec_type": "DC", "data_type": "56C' ' ", "group_var": 0, "valueContinuation": 0, "value": "", "datatype": "C", "varsize": 1, "isArray": 1, "multiplier": 56, "varlen": 56, "varlenInBits": 0},
{"filepath": "./Sample/Assembler", "filename": "ASAM1.asm", "line": "OUTLINE2 DS    0CL80 ", "var_name": "OUTLINE2", "dec_type": "DS", "data_type": "0CL80 ", "group_var": 1, "valueContinuation": 0, "value": "", "datatype": "C", "varsize": 1, "isArray": 0, "multiplier": 0, "varlen": 1, "varlenInBits": 0},
{"filepath": "./Sample/Assembler", "filename": "ASAM1.asm", "line": "         DC    CL40'....0....1....1....2....2....3....3....4' ", "var_name": "", "dec_type": "DC", "data_type": "CL40'....0....1....1....2....2....3....3....4' ", "group_var": 0, "valueContinuation": 0, "value": "....0....1....1....2....2....3....3....4", "datatype": "C", "varsize": 40, "isArray": 0, "multiplier": 1, "varlen": 40, "varlenInBits": 0},
{"filepath": "./Sample/Assembler", "filename": "ASAM1.asm", "line": "         DC    CL40'....4....5....5....6....6....7....7....8' ", "var_name": "", "dec_type": "DC", "data_type": "CL40'....4....5....5....6....6....7....7....8' ", "group_var": 0, "valueContinuation": 0, "value": "....4....5....5....6....6....7....7....8", "datatype": "C", "varsize": 40, "isArray": 0, "multiplier": 1, "varlen": 40, "varlenInBits": 0},
{"filepath": "./Sample/Assembler", "filename": "ASAM1.asm", "line": "OUTLINE3 DS    0CL80 ", "var_name": "OUTLINE3", "dec_type": "DS", "data_type": "0CL80 ", "group_var": 1, "valueContinuation": 0, "value": "", "datatype": "C", "varsize": 1, "isArray": 0, "multiplier": 0, "varlen": 1, "varlenInBits": 0},
{"filepath": "./Sample/Assembler", "filename": "ASAM1.asm", "line": "         DC    CL40'....5....0....5....0....5....0....5....0' ", "var_name": "", "dec_type": "DC", "data_type": "CL40'....5....0....5....0....5....0....5....0' ", "group_var": 0, "valueContinuation": 0, "value": "....5....0....5....0....5....0....5....0", "datatype": "C", "varsize": 40, "isArray": 0, "multiplier": 1, "varlen": 40, "varlenInBits": 0},
{"filepath": "./Sample/Assembler", "filename": "ASAM1.asm", "line": "         DC    CL40'....5....0....5....0....5....0....5....0' ", "var_name": "", "dec_type": "DC", "data_type": "CL40'....5....0....5....0....5....0....5....0' ", "group_var": 0, "valueContinuation": 0, "value": "....5....0....5....0....5....0....5....0", "datatype": "C", "varsize": 40, "isArray": 0, "multiplier": 1, "varlen": 40, "varlenInBits": 0},
{"filepath": "./Sample/Assembler", "filename": "ASAM1.asm", "line": "BLANKS   DC    80C' ' ", "var_name": "BLANKS", "dec_type": "DC", "data_type": "80C' ' ", "group_var": 0, "valueContinuation": 0, "value": "", "datatype": "C", "varsize": 1, "isArray": 1, "multiplier": 80, "varlen": 80, "varlenInBits": 0},
{"filepath": "./Sample/Assembler", "filename": "ASAM1.asm", "line": "SAVEAREA DC    18F'0' ", "var_name": "SAVEAREA", "dec_type": "DC", "data_type": "18F'0' ", "group_var": 0, "valueContinuation": 0, "value": "", "datatype": "F", "varsize": 1, "isArray": 1, "multiplier": 18, "varlen": 72, "varlenInBits": 0},
{"filepath": "./Sample/Assembler", "filename": "sample.asm", "line": "Alignfull    DS       0F            align full word boundary ", "var_name": "Alignfull", "dec_type": "DS", "data_type": "0F            align full word boundary ", "group_var": 1, "valueContinuation": 0, "value": "", "datatype": "F", "varsize": 1, "isArray": 0, "multiplier": 0, "varlen": 4, "varlenInBits": 0},
{"filepath": "./Sample/Assembler", "filename": "sample.asm", "line": "Pdetail      DS       0CL110        'person detail' ", "var_name": "Pdetail", "dec_type": "DS", "data_type": "0CL110        'person detail' ", "group_var": 1, "valueContinuation": 0, "value": "", "datatype": "C", "varsize": 1, "isArray": 0, "multiplier": 0, "varlen": 1, "varlenInBits": 0},
{"filepath": "./Sample/Assembler", "filename": "sample.asm", "line": "Pfname       DS       CL20          first name ", "var_name": "Pfname", "dec_type": "DS", "data_type": "CL20          first name ", "group_var": 0, "valueContinuation": 0, "value": "", "datatype": "C", "varsize": 20, "isArray": 0, "multiplier": 1, "varlen": 20, "varlenInBits": 0},
{"filepath": "./Sample/Assembler", "filename": "sample.asm", "line": "Plname       DS       CL20          last name ", "var_name": "Plname", "dec_type": "DS", "data_type": "CL20          last name ", "group_var": 0, "valueContinuation": 0, "value": "", "datatype": "C", "varsize": 20, "isArray": 0, "multiplier": 1, "varlen": 20, "varlenInBits": 0},
{"filepath": "./Sample/Assembler", "filename": "sample.asm", "line": "Paddress     DS       CL30          address ", "var_name": "Paddress", "dec_type": "DS", "data_type": "CL30          address ", "group_var": 0, "valueContinuation": 0, "value": "", "datatype": "C", "varsize": 30, "isArray": 0, "multiplier": 1, "varlen": 30, "varlenInBits": 0},
{"filepath": "./Sample/Assembler", "filename": "sample.asm", "line": "Pnumber      DS       CL10          phone number ", "var_name": "Pnumber", "dec_type": "DS", "data_type": "CL10          phone number ", "group_var": 0, "valueContinuation": 0, "value": "", "datatype": "C", "varsize": 10, "isArray": 0, "multiplier": 1, "varlen": 10, "varlenInBits": 0},
{"filepath": "./Sample/Assembler", "filename": "sample.asm", "line": "Pemail       DS       CL30          email address ", "var_name": "Pemail", "dec_type": "DS", "data_type": "CL30          email address ", "group_var": 0, "valueContinuation": 0, "value": "", "datatype": "C", "varsize": 30, "isArray": 0, "multiplier": 1, "varlen": 30, "varlenInBits": 0},
{"filepath": "./Sample/Assembler", "filename": "sample.asm", "line": "Var1         DS       HL20          var1 length is 20 ", "var_name": "Var1", "dec_type": "DS", "data_type": "HL20          var1 length is 20 ", "group_var": 0, "valueContinuation": 0, "value": "", "datatype": "H", "varsize": 20, "isArray": 0, "multiplier": 1, "varlen": 40, "varlenInBits": 0},
{"filepath": "./Sample/Assembler", "filename": "sample.asm", "line": "Var2         DC       CL10'ABCDE FGHI'    var2 length is 5 ", "var_name": "Var2", "dec_type": "DC", "data_type": "CL10'ABCDE FGHI'    var2 length is 5 ", "group_var": 0, "valueContinuation": 0, "value": "ABCDE FGHI", "datatype": "C", "varsize": 10, "isArray": 0, "multiplier": 1, "varlen": 10, "varlenInBits": 0},
{"filepath": "./Sample/Assembler", "filename": "sample.asm", "line": "Var3         DC       CL10'ABCDE FGHI                                  -", "var_name": "Var3", "dec_type": "DC", "data_type": "CL10'ABCDE FGHI                                  -", "group_var": 0, "valueContinuation": 1, "value": "ABCDE FGHI                                  0000000000000000000000000000000000000000", "datatype": "C", "varsize": 10, "isArray": 0, "multiplier": 1, "varlen": 10, "varlenInBits": 0},
{"filepath": "./Sample/Assembler", "filename": "sample.asm", "line": "PRVINDEX DS   264F                                                 @L1A", "var_name": "PRVINDEX", "dec_type": "DS", "data_type": "264F                                                 @L1A", "group_var": 0, "valueContinuation": 0, "value": "", "datatype": "F", "varsize": 1, "isArray": 1, "multiplier": 264, "varlen": 1056, "varlenInBits": 0}
]